setup.py
prettyprofiler/__init__.py
prettyprofiler/profile.py
prettyprofiler.egg-info/PKG-INFO
prettyprofiler.egg-info/SOURCES.txt
prettyprofiler.egg-info/dependency_links.txt
prettyprofiler.egg-info/not-zip-safe
prettyprofiler.egg-info/top_level.txt