Metadata-Version: 1.0
Name: prettyprofiler
Version: 0.1
Summary: Profiling tools
Home-page: https://github.com/BenBrostoff/prettyprofiler
Author: Ben Brostoff
Author-email: ben.brostoff@gmail.com
License: MIT
Platform: UNKNOWN
